setup.py
django_heiglerplus.egg-info/PKG-INFO
django_heiglerplus.egg-info/SOURCES.txt
django_heiglerplus.egg-info/dependency_links.txt
django_heiglerplus.egg-info/top_level.txt
heiglerplus/__init__.py
heiglerplus/tests.py