Metadata-Version: 1.0
Name: django-heiglerplus
Version: 0.1
Summary: A package with some usual apps to "usual" projects
Home-page: UNKNOWN
Author: Heigler Rocha
Author-email: lordheigler@gmail.com
License: UNKNOWN
Platform: UNKNOWN
